setup.py
django_offsite_storage.egg-info/PKG-INFO
django_offsite_storage.egg-info/SOURCES.txt
django_offsite_storage.egg-info/dependency_links.txt
django_offsite_storage.egg-info/not-zip-safe
django_offsite_storage.egg-info/pbr.json
django_offsite_storage.egg-info/requires.txt
django_offsite_storage.egg-info/top_level.txt
offsite_storage/__init__.py
offsite_storage/settings.py
offsite_storage/management/__init__.py
offsite_storage/management/commands/__init__.py
offsite_storage/management/commands/collectstatic.py
offsite_storage/storages/__init__.py
offsite_storage/storages/s3.py